TujieChanlunVol1/README.md
TujieChanlunVol1/__init__.py
TujieChanlunVol1/__main__.py
TujieChanlunVol1/file.epub
TujieChanlunVol1/index.html
TujieChanlunVol1/css/__init__.py
TujieChanlunVol1/css/annotations.css
TujieChanlunVol1/css/main.css
TujieChanlunVol1/css/normalize.css
TujieChanlunVol1/css/popup.css
TujieChanlunVol1/font/__init__.py
TujieChanlunVol1/font/fontello.eot
TujieChanlunVol1/font/fontello.svg
TujieChanlunVol1/font/fontello.ttf
TujieChanlunVol1/font/fontello.woff
TujieChanlunVol1/img/__init__.py
TujieChanlunVol1/img/annotator-glyph-sprite.png
TujieChanlunVol1/img/annotator-icon-sprite.png
TujieChanlunVol1/img/apple-touch-icon.png
TujieChanlunVol1/img/cancelfullscreen.png
TujieChanlunVol1/img/close.png
TujieChanlunVol1/img/fullscreen.png
TujieChanlunVol1/img/loader.gif
TujieChanlunVol1/img/menu-icon.png
TujieChanlunVol1/img/save.png
TujieChanlunVol1/img/saved.png
TujieChanlunVol1/img/settings-s.png
TujieChanlunVol1/img/settings.png
TujieChanlunVol1/img/star.png
TujieChanlunVol1/js/__init__.py
TujieChanlunVol1/js/epub.js
TujieChanlunVol1/js/epub.min.js
TujieChanlunVol1/js/epub.min.map
TujieChanlunVol1/js/hooks.min.js
TujieChanlunVol1/js/hooks.min.map
TujieChanlunVol1/js/reader.js
TujieChanlunVol1/js/reader.js.map
TujieChanlunVol1/js/reader.min.js
TujieChanlunVol1/js/reader.min.map
TujieChanlunVol1/js/hooks/__init__.py
TujieChanlunVol1/js/hooks/extensions/__init__.py
TujieChanlunVol1/js/hooks/extensions/highlight.js
TujieChanlunVol1/js/libs/__init__.py
TujieChanlunVol1/js/libs/jquery.min.js
TujieChanlunVol1/js/libs/localforage.min.js
TujieChanlunVol1/js/libs/screenfull.js
TujieChanlunVol1/js/libs/screenfull.min.js
TujieChanlunVol1/js/libs/zip.min.js
TujieChanlunVol1/js/plugins/__init__.py
TujieChanlunVol1/js/plugins/hypothesis.js
TujieChanlunVol1/js/plugins/search.js
tujie_chanlun_vol1-2022.10.15.0.dist-info/METADATA
tujie_chanlun_vol1-2022.10.15.0.dist-info/WHEEL
tujie_chanlun_vol1-2022.10.15.0.dist-info/entry_points.txt
tujie_chanlun_vol1-2022.10.15.0.dist-info/top_level.txt
tujie_chanlun_vol1-2022.10.15.0.dist-info/RECORD
